pynocodb/__init__.py
pynocodb/api_endpoint.py
pynocodb/api_resource.py
pynocodb/auth.py
pynocodb/base.py
pynocodb/client.py
pynocodb/column.py
pynocodb/public.py
pynocodb/record.py
pynocodb/source.py
pynocodb/storage.py
pynocodb/table.py
pynocodb/utils.py
pynocodb-0.1.0.dist-info/METADATA
pynocodb-0.1.0.dist-info/WHEEL
pynocodb-0.1.0.dist-info/RECORD
